dom/__init__.py
dom/__main__.py
window/__init__.py
adom-0.0.3.dist-info/LICENSE.txt
adom-0.0.3.dist-info/METADATA
adom-0.0.3.dist-info/WHEEL
adom-0.0.3.dist-info/entry_points.txt
adom-0.0.3.dist-info/top_level.txt
adom-0.0.3.dist-info/RECORD
